qf_aaron_alphabet/__init__.py
qf_aaron_alphabet/__main__.py
qf_aaron_alphabet-0.0.2.dist-info/METADATA
qf_aaron_alphabet-0.0.2.dist-info/WHEEL
qf_aaron_alphabet-0.0.2.dist-info/top_level.txt
qf_aaron_alphabet-0.0.2.dist-info/RECORD
