Metadata-Version: 2.1
Name: qf-aaron-alphabet
Version: 0.0.2
Summary: quickly find searchterm
Author-email: Aaron Alphabet <aaron.alphabet@posteo.org>
Requires-Python: >=3.11
